semantic_kernel_plugins/__init__.py
semantic_kernel_plugins-0.1.1.dist-info/METADATA
semantic_kernel_plugins-0.1.1.dist-info/WHEEL
semantic_kernel_plugins-0.1.1.dist-info/top_level.txt
semantic_kernel_plugins-0.1.1.dist-info/RECORD
