Metadata-Version: 2.4
Name: semantic-kernel-plugins
Version: 0.1.1
Summary: Ready-to-use plugins and tools for Semantic Kernel
Home-page: https://github.com/samitugal/semantic-kernel-tools
Author: Sami Tugal
Author-email: Sami Tugal <tugalsami@gmail.com>
License: MIT
Project-URL: Homepage, https://github.com/samitugal/semantic-kernel-plugins
Project-URL: Bug Tracker, https://github.com/samitugal/semantic-kernel-plugins/issues
Classifier: Programming Language :: Python :: 3
Classifier: License :: OSI Approved :: MIT License
Classifier: Operating System :: OS Independent
Requires-Python: >=3.8
Requires-Dist: semantic-kernel>=1.0.0
Requires-Dist: python-dotenv>=1.0.0
Requires-Dist: tavily-python>=0.5.0
Dynamic: author
Dynamic: home-page
Dynamic: requires-python
